code_agent/__init__.py
code_agent/chat_completion.py
py_code_agent_nightly-0.0.1a0.dist-info/LICENSE
py_code_agent_nightly-0.0.1a0.dist-info/METADATA
py_code_agent_nightly-0.0.1a0.dist-info/WHEEL
py_code_agent_nightly-0.0.1a0.dist-info/top_level.txt
py_code_agent_nightly-0.0.1a0.dist-info/RECORD
